docs/lakebridge/src/components/Button.tsx
docs/lakebridge/src/components/ReconcileTabs.tsx
docs/lakebridge/src/css/custom.css
docs/lakebridge/src/css/table.css
docs/lakebridge/src/pages/index.tsx
docs/lakebridge/src/theme/DocSidebarItems/index.tsx
docs/lakebridge/src/theme/Footer/index.tsx
docs/lakebridge/src/theme/Layout/index.tsx
databricks/__init__.py
databricks/labs/__init__.py
databricks/labs/lakebridge/__about__.py
databricks/labs/lakebridge/__init__.py
databricks/labs/lakebridge/cli.py
databricks/labs/lakebridge/config.py
databricks/labs/lakebridge/install.py
databricks/labs/lakebridge/lineage.py
databricks/labs/lakebridge/uninstall.py
databricks/labs/lakebridge/analyzer/__init__.py
databricks/labs/lakebridge/analyzer/lakebridge_analyzer.py
databricks/labs/lakebridge/assessments/__init__.py
databricks/labs/lakebridge/assessments/_constants.py
databricks/labs/lakebridge/assessments/configure_assessment.py
databricks/labs/lakebridge/assessments/pipeline.py
databricks/labs/lakebridge/assessments/profiler.py
databricks/labs/lakebridge/assessments/profiler_config.py
databricks/labs/lakebridge/assessments/profiler_validator.py
databricks/labs/lakebridge/assessments/dashboards/__init__.py
databricks/labs/lakebridge/assessments/dashboards/dashboard_manager.py
databricks/labs/lakebridge/assessments/dashboards/execute.py
databricks/labs/lakebridge/connections/__init__.py
databricks/labs/lakebridge/connections/credential_manager.py
databricks/labs/lakebridge/connections/database_manager.py
databricks/labs/lakebridge/connections/env_getter.py
databricks/labs/lakebridge/contexts/__init__.py
databricks/labs/lakebridge/contexts/application.py
databricks/labs/lakebridge/coverage/__init__.py
databricks/labs/lakebridge/coverage/commons.py
databricks/labs/lakebridge/coverage/lakebridge_snow_transpilation_coverage.py
databricks/labs/lakebridge/coverage/local_report.py
databricks/labs/lakebridge/coverage/sqlglot_snow_transpilation_coverage.py
databricks_labs_lakebridge-0.12.0.dist-info/METADATA
databricks_labs_lakebridge-0.12.0.dist-info/WHEEL
databricks_labs_lakebridge-0.12.0.dist-info/entry_points.txt
databricks_labs_lakebridge-0.12.0.dist-info/licenses/LICENSE
databricks_labs_lakebridge-0.12.0.dist-info/licenses/NOTICE
databricks_labs_lakebridge-0.12.0.dist-info/RECORD
